dev
dist
docs
examples
mangadap
outofdate
