Metadata-Version: 2.4
Name: sdss-mangadap
Version: 4.4.0
Summary: MaNGA Data Analysis Pipeline
Author-email: SDSS-IV/MaNGA Data Team <westfall@ucolick.org>
License: BSD 3-Clause License
Project-URL: Repository, https://github.com/sdss/mangadap
Project-URL: Documentation, https://sdss-mangadap.readthedocs.io/
Keywords: sdss,manga,astronomy,spectroscopy,galaxy,galaxies,data analysis
Classifier: Development Status :: 4 - Beta
Classifier: Intended Audience :: Science/Research
Classifier: Topic :: Scientific/Engineering :: Astronomy
Classifier: Topic :: Software Development :: Libraries :: Python Modules
Classifier: Topic :: Software Development :: User Interfaces
Classifier: Natural Language :: English
Classifier: Operating System :: OS Independent
Classifier: Programming Language :: Python
Classifier: Programming Language :: Python :: 3.11
Classifier: Programming Language :: Python :: 3.12
Classifier: Programming Language :: Python :: 3.13
Requires-Python: <3.14,>=3.11
License-File: LICENSE.md
Requires-Dist: requests>=2.25
Requires-Dist: ipython>=7.20
Requires-Dist: configobj>=5.0.6
Requires-Dist: numpy>=1.24
Requires-Dist: scipy>=1.9
Requires-Dist: matplotlib>=3.7
Requires-Dist: astropy>=6.0
Requires-Dist: shapely>=2.0
Requires-Dist: pydl>=1.0
Requires-Dist: ppxf==8.1.0
Requires-Dist: cvxopt>=1.3
Requires-Dist: vorbin==3.1.5
Provides-Extra: test
Requires-Dist: pytest>=7.1.0; extra == "test"
Requires-Dist: pytest-astropy; extra == "test"
Requires-Dist: tox; extra == "test"
Requires-Dist: pytest-cov; extra == "test"
Requires-Dist: coverage; extra == "test"
Provides-Extra: docs
Requires-Dist: sphinx<8,>6; extra == "docs"
Requires-Dist: docutils<0.22; extra == "docs"
Requires-Dist: sphinx-automodapi; extra == "docs"
Requires-Dist: sphinx_rtd_theme>3.0; extra == "docs"
Provides-Extra: dev
Requires-Dist: pytest>=7.1.0; extra == "dev"
Requires-Dist: pytest-astropy; extra == "dev"
Requires-Dist: tox; extra == "dev"
Requires-Dist: pytest-cov; extra == "dev"
Requires-Dist: coverage; extra == "dev"
Requires-Dist: sphinx<8,>6; extra == "dev"
Requires-Dist: docutils<0.22; extra == "dev"
Requires-Dist: sphinx-automodapi; extra == "dev"
Requires-Dist: sphinx_rtd_theme>3.0; extra == "dev"
Dynamic: license-file
